{"title": "Vaigai Puyal", "id": "Vadivel_Stickers", "stickers": [{"body": "IMG_0684FE91CBA3-1", "url": "mxc://matrix.org/bhVjeQlKkNLMoJoMbQRYUtgA", "info": {"w": 256, "h": 256, "size": 184435, "mimetype": "image/png", "thumbnail_url": "mxc://matrix.org/bhVjeQlKkNLMoJoMbQRYUtgA", "thumbnail_info": {"w": 256, "h": 256, "size": 184435, "mimetype": "image/png"}}, "id": "sha256:0ff93656465899522c7bed1c6074aa760749125c3299238d5b905c33eba828a9"}, {"body": "IMG_0B7D44FA8F47-1", "url": "mxc://matrix.org/RAnLzqOzlpiGuXGPYDmQRhtl", "info": {"w": 256, "h": 256, "size": 212098, "mimetype": "image/png", "thumbnail_url": "mxc://matrix.org/RAnLzqOzlpiGuXGPYDmQRhtl", "thumbnail_info": {"w": 256, "h": 256, "size": 212098, "mimetype": "image/png"}}, "id": "sha256:13ea2a23f355a02cc8bbfd76bb3bc7fc13e61625dbe995e72a814faaa8dc8afc"}, {"body": "IMG_0D3CDEC78AA0-1", "url": "mxc://matrix.org/MpKubwYvNjGWoWJPWBUqMxCN", "info": {"w": 256, "h": 256, "size": 186511, "mimetype": "image/png", "thumbnail_url": "mxc://matrix.org/MpKubwYvNjGWoWJPWBUqMxCN", "thumbnail_info": {"w": 256, "h": 256, "size": 186511, "mimetype": "image/png"}}, "id": "sha256:f7523f20492182cc9a0b5ba1e3d2e79a61e0731566e39f111da6f50102a14126"}, {"body": "IMG_0ED1A5491641-1", "url": "mxc://matrix.org/WeKQDyTPhQpBydvtmSOUoGTx", "info": {"w": 256, "h": 256, "size": 223901, "mimetype": "image/png", "thumbnail_url": "mxc://matrix.org/WeKQDyTPhQpBydvtmSOUoGTx", "thumbnail_info": {"w": 256, "h": 256, "size": 223901, "mimetype": "image/png"}}, "id": "sha256:dd1f3b49810cac9efc5de8ee7af866ed98a1a4dbcbb26bd3d98060cbb1758468"}, {"body": "IMG_1AC6D2F9FF83-1", "url": "mxc://matrix.org/AokPfCjhEzreKXtEGEpWPRdT", "info": {"w": 256, "h": 256, "size": 172797, "mimetype": "image/png", "thumbnail_url": "mxc://matrix.org/AokPfCjhEzreKXtEGEpWPRdT", "thumbnail_info": {"w": 256, "h": 256, "size": 172797, "mimetype": "image/png"}}, "id": "sha256:5915e8b9f3c2c106dc7ede60282ab7b4bd489bcf3b78446e92edcf7947d00724"}, {"body": "IMG_1AF732AEDADA-1", "url": "mxc://matrix.org/tNBZqwykyHIgcpbwETQQUsYy", "info": {"w": 256, "h": 256, "size": 251842, "mimetype": "image/png", "thumbnail_url": "mxc://matrix.org/tNBZqwykyHIgcpbwETQQUsYy", "thumbnail_info": {"w": 256, "h": 256, "size": 251842, "mimetype": "image/png"}}, "id": "sha256:0c812a963a719fa73685ba8e939ccbdfeca9fbdcfa8bd004dba773e1321ff489"}, {"body": "IMG_2749840782D4-1", "url": "mxc://matrix.org/DFdtjNRsYtkSJpGcvMOZAWxL", "info": {"w": 256, "h": 256, "size": 238936, "mimetype": "image/png", "thumbnail_url": "mxc://matrix.org/DFdtjNRsYtkSJpGcvMOZAWxL", "thumbnail_info": {"w": 256, "h": 256, "size": 238936, "mimetype": "image/png"}}, "id": "sha256:a75433fd42d58c06cce70220b5b5087f205f61619ea722664f9e07f21e1bd87d"}, {"body": "IMG_2A376590A649-1", "url": "mxc://matrix.org/OgLJVvoEzWMIzHPpgejNnoRF", "info": {"w": 256, "h": 256, "size": 186474, "mimetype": "image/png", "thumbnail_url": "mxc://matrix.org/OgLJVvoEzWMIzHPpgejNnoRF", "thumbnail_info": {"w": 256, "h": 256, "size": 186474, "mimetype": "image/png"}}, "id": "sha256:392d1f06e26c25889f5378e31e2feca5ea7f5ca4429cf70aee1a58fd61eaa621"}, {"body": "IMG_3306F5DC8951-1", "url": "mxc://matrix.org/IjkkFlJceSeqCtkCzcnigWIN", "info": {"w": 256, "h": 256, "size": 266004, "mimetype": "image/png", "thumbnail_url": "mxc://matrix.org/IjkkFlJceSeqCtkCzcnigWIN", "thumbnail_info": {"w": 256, "h": 256, "size": 266004, "mimetype": "image/png"}}, "id": "sha256:5ccf33f9443dd954ff346a3fbf8848a875b73871257d982cad6dcb680be4cb75"}, {"body": "IMG_344DA5EAF8FC-1", "url": "mxc://matrix.org/izbxYTuWCjRQNZovgiXKrvWF", "info": {"w": 256, "h": 256, "size": 209847, "mimetype": "image/png", "thumbnail_url": "mxc://matrix.org/izbxYTuWCjRQNZovgiXKrvWF", "thumbnail_info": {"w": 256, "h": 256, "size": 209847, "mimetype": "image/png"}}, "id": "sha256:660b0bf559cc5e1f3e6d3e056acd9f699461c4f4ea76b9bc7939daa1902ae4d5"}, {"body": "IMG_3F781599BEB6-1", "url": "mxc://matrix.org/uqbDARpzXRPOyRHWVSaVbGeq", "info": {"w": 256, "h": 256, "size": 248023, "mimetype": "image/png", "thumbnail_url": "mxc://matrix.org/uqbDARpzXRPOyRHWVSaVbGeq", "thumbnail_info": {"w": 256, "h": 256, "size": 248023, "mimetype": "image/png"}}, "id": "sha256:cb56372bca199dcd1f58defabcc6d64ecd4db5e368b572130f0df95b03aa6f53"}, {"body": "IMG_41993E1F7231-1", "url": "mxc://matrix.org/sgTkIdRMvKvJYTvMzCPxPFjq", "info": {"w": 256, "h": 256, "size": 189666, "mimetype": "image/png", "thumbnail_url": "mxc://matrix.org/sgTkIdRMvKvJYTvMzCPxPFjq", "thumbnail_info": {"w": 256, "h": 256, "size": 189666, "mimetype": "image/png"}}, "id": "sha256:cf2dbd5759b92f158ef2ab851e95163c410632b3fd77ae0a3928e61bc41f4012"}, {"body": "IMG_4831C2AB2C25-1", "url": "mxc://matrix.org/OKbrbQkTdqBiFbPChGQCiooB", "info": {"w": 256, "h": 256, "size": 227511, "mimetype": "image/png", "thumbnail_url": "mxc://matrix.org/OKbrbQkTdqBiFbPChGQCiooB", "thumbnail_info": {"w": 256, "h": 256, "size": 227511, "mimetype": "image/png"}}, "id": "sha256:ad4b80be8a8aa3a2450c8d2e477d969f161a2262a13d79d0f1657fe2ad1db51f"}, {"body": "IMG_494A66494A27-1", "url": "mxc://matrix.org/qJmCohiAInusXEyKcAqVhrZB", "info": {"w": 256, "h": 256, "size": 255678, "mimetype": "image/png", "thumbnail_url": "mxc://matrix.org/qJmCohiAInusXEyKcAqVhrZB", "thumbnail_info": {"w": 256, "h": 256, "size": 255678, "mimetype": "image/png"}}, "id": "sha256:1d508d24cb5e2478e5747a03d95e22b48131e16790866b0af4a8fd4c857b77b6"}, {"body": "IMG_4A62242E94F7-1", "url": "mxc://matrix.org/vyEfymVTZSvpVlxCogDLuKtM", "info": {"w": 256, "h": 256, "size": 226731, "mimetype": "image/png", "thumbnail_url": "mxc://matrix.org/vyEfymVTZSvpVlxCogDLuKtM", "thumbnail_info": {"w": 256, "h": 256, "size": 226731, "mimetype": "image/png"}}, "id": "sha256:3b50cfe0f47758e29dd239b39e06331ecd4326932be8bc40bda4ed9777874793"}, {"body": "IMG_52BBA5E31777-1", "url": "mxc://matrix.org/RZYNpxyzATdPWbcpsjTBWrHc", "info": {"w": 256, "h": 256, "size": 205667, "mimetype": "image/png", "thumbnail_url": "mxc://matrix.org/RZYNpxyzATdPWbcpsjTBWrHc", "thumbnail_info": {"w": 256, "h": 256, "size": 205667, "mimetype": "image/png"}}, "id": "sha256:e456a5cd35edc4d3992d256c3817e06e0826170104cc09f4d7016410084e8160"}, {"body": "IMG_622B8DDAAC6A-1", "url": "mxc://matrix.org/LXVhgzjVyClCihbYOymKSnVS", "info": {"w": 256, "h": 256, "size": 212580, "mimetype": "image/png", "thumbnail_url": "mxc://matrix.org/LXVhgzjVyClCihbYOymKSnVS", "thumbnail_info": {"w": 256, "h": 256, "size": 212580, "mimetype": "image/png"}}, "id": "sha256:166da517c82c9a8c02cdb0af44896b6081e06860d960fbded16fb3c80897c0b1"}, {"body": "IMG_6F70C73DECB6-1", "url": "mxc://matrix.org/YqrDGUKOxDbfgUvTVRangQqg", "info": {"w": 256, "h": 256, "size": 242528, "mimetype": "image/png", "thumbnail_url": "mxc://matrix.org/YqrDGUKOxDbfgUvTVRangQqg", "thumbnail_info": {"w": 256, "h": 256, "size": 242528, "mimetype": "image/png"}}, "id": "sha256:f29a619d81bbd1e494742070c596c9e1bda620803e23a711d84138b7e982b9aa"}, {"body": "IMG_7803B3F97705-1", "url": "mxc://matrix.org/idXuGZHPguZxluXJdMvzfBzv", "info": {"w": 256, "h": 256, "size": 195481, "mimetype": "image/png", "thumbnail_url": "mxc://matrix.org/idXuGZHPguZxluXJdMvzfBzv", "thumbnail_info": {"w": 256, "h": 256, "size": 195481, "mimetype": "image/png"}}, "id": "sha256:27bf40aa706514e3a79009d2a0d33caf14f582711fadc1f0b2286349445a8fca"}, {"body": "IMG_82E65A3FE865-1", "url": "mxc://matrix.org/CpEwlvFCpxlTExDzQFRnVTPJ", "info": {"w": 256, "h": 256, "size": 239107, "mimetype": "image/png", "thumbnail_url": "mxc://matrix.org/CpEwlvFCpxlTExDzQFRnVTPJ", "thumbnail_info": {"w": 256, "h": 256, "size": 239107, "mimetype": "image/png"}}, "id": "sha256:d0ab3f7b19c1626b8b8acfd656919cc905b42ce7503adf734f7fc728ae547aff"}, {"body": "IMG_87234E12379D-1", "url": "mxc://matrix.org/XRkxZiPkxkJbCsoDCGRrJleV", "info": {"w": 256, "h": 256, "size": 214953, "mimetype": "image/png", "thumbnail_url": "mxc://matrix.org/XRkxZiPkxkJbCsoDCGRrJleV", "thumbnail_info": {"w": 256, "h": 256, "size": 214953, "mimetype": "image/png"}}, "id": "sha256:4538a522c9fd453c2897bd6ef5817e2bd05c04cb36fbce07708c63f9c6e09870"}, {"body": "IMG_937CF2F94803-1", "url": "mxc://matrix.org/EgFLYaPJvHEDDUucrsiBQTzN", "info": {"w": 256, "h": 256, "size": 211650, "mimetype": "image/png", "thumbnail_url": "mxc://matrix.org/EgFLYaPJvHEDDUucrsiBQTzN", "thumbnail_info": {"w": 256, "h": 256, "size": 211650, "mimetype": "image/png"}}, "id": "sha256:e3eaeec1f7f552e2f6e04a9855c823eb7d0cf269bce5f5b935f454f5fa0602ff"}, {"body": "IMG_99F647AF6C7B-1", "url": "mxc://matrix.org/MmBHnvfQdwmxxbDyzvlaTVZy", "info": {"w": 256, "h": 256, "size": 210924, "mimetype": "image/png", "thumbnail_url": "mxc://matrix.org/MmBHnvfQdwmxxbDyzvlaTVZy", "thumbnail_info": {"w": 256, "h": 256, "size": 210924, "mimetype": "image/png"}}, "id": "sha256:80687bd9d91ba12b3813a68100c6281d5aba10a2b8dde53bfa804705f585f055"}, {"body": "IMG_A3333D06F269-1", "url": "mxc://matrix.org/RSvEECxSQvPYjMpAUQnDHEla", "info": {"w": 256, "h": 256, "size": 229785, "mimetype": "image/png", "thumbnail_url": "mxc://matrix.org/RSvEECxSQvPYjMpAUQnDHEla", "thumbnail_info": {"w": 256, "h": 256, "size": 229785, "mimetype": "image/png"}}, "id": "sha256:d5d5c847394dc2c76d9a9c1d01f83a57f443c6e9b9139e9cd7cd0f3ee8abb0c4"}, {"body": "IMG_B3AAC15DE816-1", "url": "mxc://matrix.org/drRWAezfITRcjOqGnPXNwYBp", "info": {"w": 256, "h": 256, "size": 227869, "mimetype": "image/png", "thumbnail_url": "mxc://matrix.org/drRWAezfITRcjOqGnPXNwYBp", "thumbnail_info": {"w": 256, "h": 256, "size": 227869, "mimetype": "image/png"}}, "id": "sha256:319d7c2f3437e158299fd67c1991ddfdd3b6ac9f4dabd7dd44005ad16ad06ad8"}, {"body": "IMG_B6939204103F-1", "url": "mxc://matrix.org/XHjKXfUKgqQjlkeTsYDcMItq", "info": {"w": 256, "h": 256, "size": 226787, "mimetype": "image/png", "thumbnail_url": "mxc://matrix.org/XHjKXfUKgqQjlkeTsYDcMItq", "thumbnail_info": {"w": 256, "h": 256, "size": 226787, "mimetype": "image/png"}}, "id": "sha256:c32b76e3e01a818b6268cd8667c0e1391ec9b0398f2c06da1ae932b362142efb"}, {"body": "IMG_B792F40928FC-1", "url": "mxc://matrix.org/fnsiiigHjKDJImfFihyvDVaL", "info": {"w": 256, "h": 256, "size": 220776, "mimetype": "image/png", "thumbnail_url": "mxc://matrix.org/fnsiiigHjKDJImfFihyvDVaL", "thumbnail_info": {"w": 256, "h": 256, "size": 220776, "mimetype": "image/png"}}, "id": "sha256:992f7c45f6fb404acd6e3060bc14dc3dc4624aeef3a4e13c37de48e52856e8c1"}, {"body": "IMG_C751CEB5B807-1", "url": "mxc://matrix.org/CzGLCGnEoHmValfFWHDatsbd", "info": {"w": 256, "h": 256, "size": 180909, "mimetype": "image/png", "thumbnail_url": "mxc://matrix.org/CzGLCGnEoHmValfFWHDatsbd", "thumbnail_info": {"w": 256, "h": 256, "size": 180909, "mimetype": "image/png"}}, "id": "sha256:af7d122037d0204829daf3b098ab5825fd320407bc1ca48cb81d275a36aa7eac"}, {"body": "IMG_CAED9FF72310-1", "url": "mxc://matrix.org/lYEoHxeFTpOQaChENQkxYugO", "info": {"w": 256, "h": 256, "size": 261323, "mimetype": "image/png", "thumbnail_url": "mxc://matrix.org/lYEoHxeFTpOQaChENQkxYugO", "thumbnail_info": {"w": 256, "h": 256, "size": 261323, "mimetype": "image/png"}}, "id": "sha256:b276abc0df860e51f4e7e5e9d65460306059a3ce3f9c46add8377d40c16458f8"}, {"body": "IMG_D8F80D81BE82-1", "url": "mxc://matrix.org/yzlctQWfdiKqktcfREKCFLFm", "info": {"w": 256, "h": 256, "size": 229526, "mimetype": "image/png", "thumbnail_url": "mxc://matrix.org/yzlctQWfdiKqktcfREKCFLFm", "thumbnail_info": {"w": 256, "h": 256, "size": 229526, "mimetype": "image/png"}}, "id": "sha256:40232499d018bad561bb964a15555088e77a86fb00f21e7cd01b92ef145fd7e3"}, {"body": "IMG_D92190A7FBA6-1", "url": "mxc://matrix.org/ptRvUutdvmctIsLeEYQBBziE", "info": {"w": 256, "h": 256, "size": 195401, "mimetype": "image/png", "thumbnail_url": "mxc://matrix.org/ptRvUutdvmctIsLeEYQBBziE", "thumbnail_info": {"w": 256, "h": 256, "size": 195401, "mimetype": "image/png"}}, "id": "sha256:9372c2e481e25fb5926d962bce67f5dc7433ad60cdf52ef68bde8531fd3ec02f"}, {"body": "IMG_DF7797B9B32B-1", "url": "mxc://matrix.org/ZlrjaJsBzDwebDiKuvetVzPU", "info": {"w": 256, "h": 256, "size": 259666, "mimetype": "image/png", "thumbnail_url": "mxc://matrix.org/ZlrjaJsBzDwebDiKuvetVzPU", "thumbnail_info": {"w": 256, "h": 256, "size": 259666, "mimetype": "image/png"}}, "id": "sha256:5f79049b4bcb247b97fa3c0373f01ca257ae02fc09e45caa4fc28e3017f365c5"}, {"body": "IMG_EBE9AAD849B2-1", "url": "mxc://matrix.org/MsRXoKnwyVRVwkOYoBCrQYCU", "info": {"w": 256, "h": 256, "size": 251428, "mimetype": "image/png", "thumbnail_url": "mxc://matrix.org/MsRXoKnwyVRVwkOYoBCrQYCU", "thumbnail_info": {"w": 256, "h": 256, "size": 251428, "mimetype": "image/png"}}, "id": "sha256:6eb2f5b78a736bd87230ec2d17d4add8511063dd89b9551ed13bb2377d50d0c8"}, {"body": "IMG_ED46DA96B522-1", "url": "mxc://matrix.org/EjFMkzHHspMgKABgSvCtfWRh", "info": {"w": 256, "h": 256, "size": 240382, "mimetype": "image/png", "thumbnail_url": "mxc://matrix.org/EjFMkzHHspMgKABgSvCtfWRh", "thumbnail_info": {"w": 256, "h": 256, "size": 240382, "mimetype": "image/png"}}, "id": "sha256:f9664193fb46d60747dde2b2fe66e018b9c2493a0b2d96bb4a5139a625fc68e6"}, {"body": "IMG_FA7CFC5ACA91-1", "url": "mxc://matrix.org/bHLEsaCOnSMpXYhCJsmlbshC", "info": {"w": 256, "h": 256, "size": 177186, "mimetype": "image/png", "thumbnail_url": "mxc://matrix.org/bHLEsaCOnSMpXYhCJsmlbshC", "thumbnail_info": {"w": 256, "h": 256, "size": 177186, "mimetype": "image/png"}}, "id": "sha256:41c47343903fbf3588c66c4b425936770f392825330527c2e51312a6d89a3f6f"}]}